Lab1/exercise2/CA/exercise2.v
module exercise2(a, b, c, d, f, g);

input a, b, c, d;
output f, g;
wire x, y;


// XOR ^ f
// NAND ^ ~& ab
// nor ~| g
		assign f = (d^(~(a&b))^c);
		assign g = (~(b|c|d));

endmodule

Lab1/exercise2/GLP/exercise2_tb.v
`timescale 1ns/1ns
`include "exercise2.v" //Name of the Verilog file



module exercise2_tb();
reg a,b,c,d;	//Input
wire f,g;		//Output

exercise2 ex2(a,b,c,d, f,g); //Instantiation of the module

initial
begin

$dumpfile("exercise2_tb.vcd");
$dumpvars(0, exercise2_tb);

		a=1'b0; b=1'b0; c=1'b0;	d=1'b0;
		#20;	
		a=1'b0; b=1'b0; c=1'b0;	d=1'b1;
		#20;	
		a=1'b0; b=1'b0; c=1'b1;	d=1'b0;
		#20;	
		a=1'b0; b=1'b0; c=1'b1;	d=1'b1;
		#20;	
		a=1'b0; b=1'b1; c=1'b0;	d=1'b0;
		#20;	
		a=1'b0; b=1'b1; c=1'b0;	d=1'b1;
		#20;	
		a=1'b0; b=1'b1; c=1'b1;	d=1'b0;
		#20;	
		a=1'b0; b=1'b1; c=1'b1;	d=1'b1;
		#20;	
		a=1'b1; b=1'b0; c=1'b0;	d=1'b0;
		#20;	
		a=1'b1; b=1'b0; c=1'b0;	d=1'b1;
		#20;	
		a=1'b1; b=1'b0; c=1'b1;	d=1'b0;
		#20;	
		a=1'b1; b=1'b0; c=1'b1;	d=1'b1;
		#20;	
		a=1'b1; b=1'b1; c=1'b0;	d=1'b0;
		#20;	
		a=1'b1; b=1'b1; c=1'b0;	d=1'b1;
		#20;	
		a=1'b1; b=1'b1; c=1'b1;	d=1'b0;
		#20;	
		a=1'b1; b=1'b1; c=1'b1;	d=1'b1;
		#20;	

$display("Test complete");
end
endmodule

Lab1/exercise2/CA/exercise2_tb.vcd
$date
	Thu Aug 25 10:08:22 2022
$end
$version
	Icarus Verilog
$end
$timescale
	1ns
$end
$scope module exercise2_tb $end
$var wire 1 ! g $end
$var wire 1 " f $end
$var reg 1 # a $end
$var reg 1 $ b $end
$var reg 1 % c $end
$var reg 1 & d $end
$scope module ex2 $end
$var wire 1 # a $end
$var wire 1 $ b $end
$var wire 1 % c $end
$var wire 1 & d $end
$var wire 1 " f $end
$var wire 1 ! g $end
$upscope $end
$upscope $end
$enddefinitions $end
#0
$dumpvars
0&
0%
0$
0#
1"
1!
$end
#20
0"
0!
1&
#40
0"
0&
1%
#60
1"
1&
#80
1"
0&
0%
1$
#100
0"
1&
#120
0"
0&
1%
#140
1"
1&
#160
1!
1"
0&
0%
0$
1#
#180
0"
0!
1&
#200
0"
0&
1%
#220
1"
1&
#240
0"
0&
0%
1$
#260
1"
1&
#280
1"
0&
1%
#300
0"
1&
