Lab1/exercise1/GLP/exercise1.v
module exercise1(a, b, c, d, f);

input a,b,c,d;
output f;

	and (k,a,b);
	or (g,k,c);
	not (l,g);
	or(e,g,d);
	and (m,l,d);
	and (f,e,m);
	
endmodule

Lab1/exercise1/GLP/exercise1_tb.v
`timescale 1ns/1ns
`include "exercise1.v"

//Name of the Verilog file
module exercise1_tb();

reg a,b,c,d;
//Input

wire f;
//Output

exercise1 ex1(a,b,c,d, f); //Instantiation of the module

initial
begin

	$dumpfile("exercise1_tb.vcd");
	$dumpvars(0, exercise1_tb);


	a=1'b0; b=1'b0; c=1'b0; d=1'b0;
	#20;
	a=1'b0; b=1'b0; c=1'b0; d=1'b1;
	#20;
	a=1'b0; b=1'b0; c=1'b1; d=1'b0;
	#20;
	a=1'b0; b=1'b0; c=1'b1; d=1'b1;
	#20;
	a=1'b0; b=1'b1; c=1'b0; d=1'b0;
	#20;
	a=1'b0; b=1'b1; c=1'b0; d=1'b1;
	#20;
	a=1'b0; b=1'b1; c=1'b1; d=1'b0;
	#20;
	a=1'b0; b=1'b1; c=1'b1; d=1'b1;
	#20;
	a=1'b1; b=1'b0; c=1'b0; d=1'b0;
	#20;
	a=1'b1; b=1'b0; c=1'b0; d=1'b1;
	#20;
	a=1'b1; b=1'b0; c=1'b1; d=1'b0;
	#20;
	a=1'b1; b=1'b0; c=1'b1; d=1'b1;
	#20;
	a=1'b1; b=1'b1; c=1'b0; d=1'b0;
	#20;
	a=1'b1; b=1'b1; c=1'b0; d=1'b1;
	#20;
	a=1'b1; b=1'b1; c=1'b1; d=1'b0;
	#20;
	a=1'b1; b=1'b1; c=1'b1; d=1'b1;
	#20;

$display("Test complete");
end
endmodule

Lab1/exercise1/GLP/exercise1_tb.vcd
$date
	Thu Aug 25 10:25:42 2022
$end
$version
	Icarus Verilog
$end
$timescale
	1ns
$end
$scope module exercise1_tb $end
$var wire 1 ! f $end
$var reg 1 " a $end
$var reg 1 # b $end
$var reg 1 $ c $end
$var reg 1 % d $end
$scope module ex1 $end
$var wire 1 " a $end
$var wire 1 # b $end
$var wire 1 $ c $end
$var wire 1 % d $end
$var wire 1 & e $end
$var wire 1 ! f $end
$var wire 1 ' g $end
$var wire 1 ( k $end
$var wire 1 ) l $end
$var wire 1 * m $end
$upscope $end
$upscope $end
$enddefinitions $end
#0
$dumpvars
0*
1)
0(
0'
0&
0%
0$
0#
0"
0!
$end
#20
1!
1&
1*
1%
#40
0!
0)
0*
1'
0%
1$
#60
1%
#80
1)
0&
0'
0%
0$
1#
#100
1!
1&
1*
1%
#120
0!
0)
0*
1'
0%
1$
#140
1%
#160
1)
0&
0'
0%
0$
0#
1"
#180
1!
1&
1*
1%
#200
0!
0)
0*
1'
0%
1$
#220
1%
#240
1(
0%
0$
1#
#260
1%
#280
0%
1$
#300
1%
